gh_subdir
