Metadata-Version: 2.1
Name: gh-subdir
Version: 1.0.0
Summary: A Python module for installing GitHub subdirectories.
Home-page: https://github.com/reecevela/gh-subdir-py
Author: Reece Vela
Author-email: reecevela@outlook.com
License: GPLv3
Keywords: github directory download python
Platform: UNKNOWN
Classifier: Development Status :: 3 - Alpha
Classifier: Intended Audience :: Developers
Classifier: License :: OSI Approved :: GNU General Public License v3 (GPLv3)
Classifier: Programming Language :: Python :: 3
